stela_mcp/__init__.py
stela_mcp/filesystem.py
stela_mcp/security.py
stela_mcp/server.py
stela_mcp/shell.py
stela_mcp-0.5.0.dist-info/METADATA
stela_mcp-0.5.0.dist-info/WHEEL
stela_mcp-0.5.0.dist-info/entry_points.txt
stela_mcp-0.5.0.dist-info/licenses/LICENSE
stela_mcp-0.5.0.dist-info/RECORD
