Metadata-Version: 2.4
Name: stela-mcp
Version: 0.5.0
Summary: A Python implementation of a Model Context Protocol server
Project-URL: Homepage, https://github.com/Sachin-Bhat/stela-mcp
Project-URL: Documentation, https://github.com/Sachin-Bhat/stela-mcp#readme
Project-URL: Repository, https://github.com/Sachin-Bhat/stela-mcp.git
Project-URL: Issues, https://github.com/Sachin-Bhat/stela-mcp/issues
Author-email: Sachin Bhat <sachubhat17@gmail.com>
License-Expression: Apache-2.0
License-File: LICENSE
Classifier: Development Status :: 3 - Alpha
Classifier: Intended Audience :: Developers
Classifier: License :: OSI Approved :: Apache Software License
Classifier: Programming Language :: Python :: 3
Classifier: Programming Language :: Python :: 3.10
Classifier: Programming Language :: Python :: 3.11
Classifier: Programming Language :: Python :: 3.12
Requires-Python: >=3.10
Requires-Dist: fastapi>=0.115.12
Requires-Dist: loguru>=0.7.3
Requires-Dist: mcp[cli]>=1.1.0
Requires-Dist: psutil>=7.0.0
Requires-Dist: typing-extensions>=4.13.0
